Metadata-Version: 2.1
Name: zesty.zbs-api-securonix-agent-baseurl-debug
Version: 2.0.2023.7.26.1690405274
Summary: Zesty Disk API
Home-page: https://github.com/javatechy/dokr
Author: Zesty.co
Author-email: rnd@cloudvisor.co
License: UNKNOWN
Platform: UNKNOWN
Classifier: Programming Language :: Python :: 3
Classifier: License :: OSI Approved :: MIT License
Classifier: Operating System :: OS Independent
Requires-Dist: requests
Requires-Dist: zesty.zesty-id
